<?xml version="1.0" encoding="UTF-8"?>
<!DOCTYPE rules SYSTEM "https://resources.jetbrains.com/writerside/1.0/redirection-rules.dtd">
<rules>
    <!-- format is as follows
    <rule id="<unique id>">
        <accepts>page.html</accepts>
    </rule>
    -->
    <rule id="b4cb068">
        <description>Created after removal of "Обзор C# и .NET" from C# Tutorial</description>
        <accepts>Обзор-C-и-NET.html</accepts>
    </rule>
    <rule id="51004239">
        <description>Created after removal of "Эпизод 1. Основы язка C#" from Полный учебный курс по C# и .NET (уроки и
            практические задачи)
        </description>
        <accepts>Эпизод-1-Основы-язка-C.html</accepts>
    </rule>
    <rule id="672f1856">
        <description>Created after removal of "This is the first topic" from Полный учебный курс по C# и .NET (уроки и
            практические задачи)
        </description>
        <accepts>Default-topic.html</accepts>
    </rule>
</rules>